Metadata-Version: 1.0
Name: rat-distributions
Version: 0.1
Summary: Gaussian and Binomial distributions
Home-page: UNKNOWN
Author: Ratinesh Kumar
Author-email: a13888120@gmail.com
License: UNKNOWN
Platform: UNKNOWN
